bestbuy/__init__.py
bestbuy/exceptions.py
bestbuy/loggers.py
bestbuy/py.typed
bestbuy/typing.py
bestbuy/clients/__init__.py
bestbuy/clients/base.py
bestbuy/clients/catalog.py
bestbuy/clients/commerce.py
bestbuy/configs/__init__.py
bestbuy/configs/base.py
bestbuy/configs/catalog.py
bestbuy/configs/commerce.py
bestbuy/models/__init__.py
bestbuy/models/catalog.py
bestbuy/models/commerce.py
bestbuy/operations/__init__.py
bestbuy/operations/base.py
bestbuy/operations/catalog.py
bestbuy/operations/commerce.py
bestbuy/operations/pagination.py
bestbuy/utils/__init__.py
bestbuy/utils/encryption.py
bestbuy/utils/errors.py
python_bestbuy-0.1.0.dist-info/METADATA
python_bestbuy-0.1.0.dist-info/WHEEL
python_bestbuy-0.1.0.dist-info/licenses/LICENSE
python_bestbuy-0.1.0.dist-info/RECORD
