Metadata-Version: 2.4
Name: python-bestbuy
Version: 0.1.0
Summary: Python client library for Best Buy's Catalog and Commerce APIs
Project-URL: Homepage, https://github.com/bbify/python-bestbuy
Project-URL: Repository, https://github.com/bbify/python-bestbuy
Project-URL: Issues, https://github.com/bbify/python-bestbuy/issues
Project-URL: Changelog, https://github.com/bbify/python-bestbuy/blob/main/CHANGELOG.md
Author-email: Michael Lavers <kolanos@gmail.com>
License-Expression: MIT
License-File: LICENSE
Keywords: api,bestbuy,catalog,commerce,ecommerce
Classifier: Development Status :: 3 - Alpha
Classifier: Intended Audience :: Developers
Classifier: License :: OSI Approved :: MIT License
Classifier: Operating System :: OS Independent
Classifier: Programming Language :: Python :: 3
Classifier: Programming Language :: Python :: 3.10
Classifier: Programming Language :: Python :: 3.11
Classifier: Programming Language :: Python :: 3.12
Classifier: Programming Language :: Python :: 3.13
Classifier: Typing :: Typed
Requires-Python: >=3.10
Requires-Dist: cryptography>=35.0.0
Requires-Dist: httpx>=0.23.0
Requires-Dist: pydantic-xml>=2.0.0
